pynets/__about__.py
pynets/__init__.py
pynets/_version.py
pynets/advanced.yaml
pynets/citations.py
pynets/cli/__init__.py
pynets/cli/pynets_benchmark.py
pynets/cli/pynets_bids.py
pynets/cli/pynets_cloud.py
pynets/cli/pynets_config.py
pynets/cli/pynets_predict.py
pynets/cli/pynets_run.py
pynets/core/__init__.py
pynets/core/cloud.py
pynets/core/database.py
pynets/core/interfaces.py
pynets/core/nodemaker.py
pynets/core/thresholding.py
pynets/core/utils.py
pynets/core/workflows.py
pynets/core/tests/__init__.py
pynets/core/tests/conftest.py
pynets/core/tests/test_nodemaker.py
pynets/core/tests/test_refs.py
pynets/core/tests/test_thresholding.py
pynets/core/tests/test_utils.py
pynets/dmri/__init__.py
pynets/dmri/estimation.py
pynets/dmri/interfaces.py
pynets/dmri/track.py
pynets/dmri/utils.py
pynets/dmri/tests/__init__.py
pynets/dmri/tests/conftest.py
pynets/dmri/tests/test_estimation.py
pynets/dmri/tests/test_track.py
pynets/dmri/tests/test_utils.py
pynets/dmri/tests/test_workflows_dwi.py
pynets/fmri/__init__.py
pynets/fmri/clustering.py
pynets/fmri/estimation.py
pynets/fmri/interfaces.py
pynets/fmri/tests/__init__.py
pynets/fmri/tests/conftest.py
pynets/fmri/tests/test_clustering.py
pynets/fmri/tests/test_estimation.py
pynets/fmri/tests/test_workflows_func.py
pynets/plotting/__init__.py
pynets/plotting/adjacency.py
pynets/plotting/brain.py
pynets/plotting/connectogram.py
pynets/plotting/interfaces.py
pynets/plotting/tests/__init__.py
pynets/plotting/tests/conftest.py
pynets/plotting/tests/test_adjacency.py
pynets/plotting/tests/test_brain.py
pynets/registration/__init__.py
pynets/registration/interfaces.py
pynets/registration/register.py
pynets/registration/utils.py
pynets/registration/tests/__init__.py
pynets/registration/tests/test_utils.py
pynets/statistics/__init__.py
pynets/statistics/interfaces.py
pynets/statistics/utils.py
pynets/statistics/group/__init__.py
pynets/statistics/group/benchmarking.py
pynets/statistics/group/prediction.py
pynets-1.30.dist-info/AUTHORS.rst
pynets-1.30.dist-info/METADATA
pynets-1.30.dist-info/NOTICE
pynets-1.30.dist-info/WHEEL
pynets-1.30.dist-info/dependency_links.txt
pynets-1.30.dist-info/entry_points.txt
pynets-1.30.dist-info/top_level.txt
pynets-1.30.dist-info/RECORD
