Metadata-Version: 2.1
Name: pynets
Version: 1.30
Summary: A Reproducible Workflow for Structural and Functional Connectome Ensemble Learning
Home-page: https://github.com/dPys/pynets
Author: Derek Pisner
Author-email: dpisner@utexas.edu
License: GNU Affero General Public License v3 or later (AGPLv3+)
Keywords: pynets
Platform: UNKNOWN
Classifier: Development Status :: 5 - Production/Stable
Classifier: Intended Audience :: Developers
Classifier: License :: OSI Approved :: GNU Affero General Public License v3 or later (AGPLv3+)
Classifier: Natural Language :: English
Classifier: Programming Language :: Python :: 3.8
Classifier: Programming Language :: Python :: 3.9
License-File: NOTICE
License-File: AUTHORS.rst
Requires-Dist: matplotlib (>=3.0.0)
Requires-Dist: pickle5 (>=0.0.11)
Requires-Dist: dill (>=0.3.2)
Requires-Dist: statsmodels (>=0.11.1)
Requires-Dist: Sphinx (>=1.4.8)
Requires-Dist: sphinx-rtd-theme (>=0.4.3)
Requires-Dist: sphinx-argparse (>=0.2.5)
Requires-Dist: docutils (>=0.14.0)
Requires-Dist: numpy (>=1.19.5)
Requires-Dist: numpydoc (>=1.1.0)
Requires-Dist: requests (>=2.26.0)
Requires-Dist: joblib (>=1.0.1)
Requires-Dist: pandas (>=0.24.2)
Requires-Dist: psutil (>=5.6.1)
Requires-Dist: scipy (>=1.4.1)
Requires-Dist: setuptools (>=52.0.0)
Requires-Dist: nibabel (>=3.2.1)
Requires-Dist: indexed-gzip (>=1.4.0)
Requires-Dist: seaborn (>=0.11.0)
Requires-Dist: networkx (>=2.5.1)
Requires-Dist: nipype (==1.5.1)
Requires-Dist: scikit-learn (==0.24.1)
Requires-Dist: dipy (>=1.5.0)
Requires-Dist: boto3 (>=1.9.111)
Requires-Dist: pybids (>=0.6.4)
Requires-Dist: colorama (>=0.3.9)
Requires-Dist: python-louvain (>=0.13)
Requires-Dist: graspologic (==1.0.0.dev1791934871)
Requires-Dist: sqlalchemy (~=1.3.1)
Requires-Dist: h5py (>=2.10.0)
Requires-Dist: scikit-image (>=0.14.2)
Requires-Dist: six (>=1.12.0)
Requires-Dist: pyyaml (>=6.0)
Requires-Dist: urllib3 (>=1.25.4)
Requires-Dist: mplcyberpunk (>=0.1.11)
Requires-Dist: numba (>=0.51.2)
Provides-Extra: datalad
Requires-Dist: datalad ; extra == 'datalad'
Provides-Extra: doc
Requires-Dist: nbsphinx ; extra == 'doc'
Requires-Dist: packaging ; extra == 'doc'
Requires-Dist: pydot (>=1.2.3) ; extra == 'doc'
Requires-Dist: pydotplus ; extra == 'doc'
Requires-Dist: sphinx (>=1.5.3) ; extra == 'doc'
Requires-Dist: numpydoc (>=0.8.0) ; extra == 'doc'
Requires-Dist: sphinx-argparse ; extra == 'doc'
Requires-Dist: sphinx-rtd-theme ; extra == 'doc'
